djangocms_zb_repository/__init__.py
djangocms_zb_repository/apps.py
djangocms_zb_repository/cms_plugins.py
djangocms_zb_repository/models.py
djangocms_zb_repository/tests.py
djangocms_zb_repository/views.py
djangocms_zb_repository/lib/__init__.py
djangocms_zb_repository/lib/choices.py
djangocms_zb_repository/locale/es/LC_MESSAGES/django.mo
djangocms_zb_repository/locale/es/LC_MESSAGES/django.po
djangocms_zb_repository/migrations/0001_initial.py
djangocms_zb_repository/migrations/0002_alter_zibanurepositorypluginmodel_order.py
djangocms_zb_repository/migrations/__init__.py
djangocms_zb_repository/static/djangocms_zb_repository/css/base.css
djangocms_zb_repository/templates/__init__.py
djangocms_zb_repository/templates/djangocms_zb_repository/base.html
djangocms_zb_repository/templates/djangocms_zb_repository/bootstrap4/style_one/plugin.html
djangocms_zb_repository/templates/djangocms_zb_repository/bootstrap4/style_one/includes/category.html
djangocms_zb_repository/templates/djangocms_zb_repository/bootstrap4/style_one/includes/file_list.html
djangocms_zb_repository/templates/djangocms_zb_repository/bootstrap4/style_one/includes/pagination.html
djangocms_zb_repository/templates/djangocms_zb_repository/bootstrap4/style_three/plugin.html
djangocms_zb_repository/templates/djangocms_zb_repository/bootstrap4/style_three/includes/category.html
djangocms_zb_repository/templates/djangocms_zb_repository/bootstrap4/style_three/includes/file_list.html
djangocms_zb_repository/templates/djangocms_zb_repository/bootstrap4/style_three/includes/pagination.html
djangocms_zb_repository/templates/djangocms_zb_repository/bootstrap4/style_two/plugin.html
djangocms_zb_repository/templates/djangocms_zb_repository/bootstrap4/style_two/includes/category.html
djangocms_zb_repository/templates/djangocms_zb_repository/bootstrap4/style_two/includes/file_list.html
djangocms_zb_repository/templates/djangocms_zb_repository/bootstrap4/style_two/includes/pagination.html
djangocms_zb_repository-1.0.4.dist-info/licenses/LICENSE
djangocms_zb_repository-1.0.4.dist-info/METADATA
djangocms_zb_repository-1.0.4.dist-info/WHEEL
djangocms_zb_repository-1.0.4.dist-info/top_level.txt
djangocms_zb_repository-1.0.4.dist-info/RECORD
